LICENSE.txt
MANIFEST.in
README.txt
collectd.py
setup.py
unit_tests.py
collectd.egg-info/PKG-INFO
collectd.egg-info/SOURCES.txt
collectd.egg-info/dependency_links.txt
collectd.egg-info/top_level.txt
docs/.buildinfo
docs/genindex.html
docs/index.html
docs/objects.inv
docs/search.html
docs/searchindex.js
docs/_sources/index.txt
docs/_static/basic.css
docs/_static/default.css
docs/_static/doctools.js
docs/_static/file.png
docs/_static/jquery.js
docs/_static/minus.png
docs/_static/plus.png
docs/_static/pygments.css
docs/_static/searchtools.js
examples/basic.py
examples/primes.py